[{"place_id": 205243550, "licence": "Data \u00a9 OpenStreetMap contributors, ODbL 1.0. https://osm.org/copyright", "osm_type": "way", "osm_id": 469036157, "boundingbox": ["37.3826074", "37.3829453", "127.1258262", "127.1262469"], "lat": "37.38277635", "lon": "127.12603655705388", "display_name": "\uc11c\ud6041\ub3d9 \ud589\uc815\ubcf5\uc9c0\uc13c\ud130, 35, Junganggongwon-ro 39beon-gil, Bundang-gu, Seongnam-si, Gyeonggi, 13588, South Korea", "class": "amenity", "type": "townhall", "importance": 0.101, "geojson": {"type": "Polygon", "coordinates": [[[127.1258262, 37.3828041], [127.1260529, 37.3826074], [127.1262469, 37.3827486], [127.1260203, 37.3829453], [127.1258262, 37.3828041]]]}}, {"place_id": 205243576, "licence": "Data \u00a9 OpenStreetMap contributors, ODbL 1.0. https://osm.org/copyright", "osm_type": "way", "osm_id": 469036157, "boundingbox": ["37.3826074", "37.3829453", "127.1258262", "127.1262469"], "lat": "37.38277635", "lon": "127.12603655705388", "display_name": "\uc11c\ud6041\ub3d9 \ud589\uc815\ubcf5\uc9c0\uc13c\ud130, 35, Junganggongwon-ro 39beon-gil, Bundang-gu, Seongnam-si, Gyeonggi, 13588, South Korea", "class": "office", "type": "government", "importance": 0.101, "geojson": {"type": "Polygon", "coordinates": [[[127.1258262, 37.3828041], [127.1260529, 37.3826074], [127.1262469, 37.3827486], [127.1260203, 37.3829453], [127.1258262, 37.3828041]]]}}]